transformers_domain_adaptation/__init__.py
transformers_domain_adaptation/type.py
transformers_domain_adaptation/vocab_augmentor.py
transformers_domain_adaptation/data_selection/__init__.py
transformers_domain_adaptation/data_selection/data_selector.py
transformers_domain_adaptation/data_selection/metrics/__init__.py
transformers_domain_adaptation/data_selection/metrics/diversity.py
transformers_domain_adaptation/data_selection/metrics/similarity.py
transformers_domain_adaptation-0.3.1.dist-info/METADATA
transformers_domain_adaptation-0.3.1.dist-info/WHEEL
transformers_domain_adaptation-0.3.1.dist-info/top_level.txt
transformers_domain_adaptation-0.3.1.dist-info/RECORD
