Metadata-Version: 2.1
Name: transformers-domain-adaptation
Version: 0.3.1
Summary: Adapt Transformer-based language models to new text domains
Home-page: https://github.com/georgianpartners/Transformers-Domain-Adaptation
Author: Christopher Tee
Author-email: chris@georgian.io
License: MIT
Keywords: transformers,tokenizers,huggingface,pytorch,domain-adaptation,transfer-learning,natural-language-processing
Platform: UNKNOWN
Classifier: Development Status :: 3 - Alpha
Classifier: Intended Audience :: Developers
Classifier: Programming Language :: Python :: 3
Classifier: Programming Language :: Python :: 3.6
Classifier: Programming Language :: Python :: 3.7
Classifier: Programming Language :: Python :: 3.8
Classifier: License :: OSI Approved :: MIT License
Classifier: Topic :: Scientific/Engineering :: Artificial Intelligence
Classifier: Topic :: Text Processing :: General
Requires-Python: >=3.6
Requires-Dist: transformers (<5,>=4)
Requires-Dist: tokenizers (<0.10,>=0.9)
Requires-Dist: datasets (<1.3,>=1.2)
Requires-Dist: pandas
Requires-Dist: torch (<1.8,>=1.7)
Requires-Dist: scipy (==1.5.4)
Requires-Dist: scikit-learn
Requires-Dist: tqdm
